Metadata-Version: 1.1
Name: arctool
Version: 0.13.2
Summary: arctool is a tool for archiving data
Home-page: https://github.com/JIC-CSB/arctool
Author: Tjelvar Olsson
Author-email: tjelvar.olsson@jic.ac.uk
License: MIT
Download-URL: https://github.com/JIC-CSB/arctool/tarball/0.13.2
Platform: UNKNOWN
